{"cameraMode":{"drawMode":0,"name":"Shaded","section":"Shading Mode"},"sceneLighting":true,"audioPlay":false,"sceneViewState":{"m_AlwaysRefresh":false,"showFog":true,"showSkybox":true,"showFlares":true,"showImageEffects":true,"showParticleSystems":true,"showVisualEffectGraphs":true,"m_FxEnabled":true},"in2DMode":false,"pivot":{"x":5.525705337524414,"y":4.432303428649902,"z":-4.556142330169678},"rotation":{"x":0.40332531929016116,"y":-0.09039504826068878,"z":0.04028245061635971,"w":0.9097765684127808},"size":0.4645138680934906,"orthographic":false}